LICENSE
MANIFEST.in
README.md
TODO.md
requirements.txt
setup.py
pyshield/__init__.py
pyshield/__main__.py
pyshield/cli.py
pyshield/encryptor.py
pyshield/loader.py
pyshield/utils.py
pyshield_encryptor.egg-info/PKG-INFO
pyshield_encryptor.egg-info/SOURCES.txt
pyshield_encryptor.egg-info/dependency_links.txt
pyshield_encryptor.egg-info/entry_points.txt
pyshield_encryptor.egg-info/not-zip-safe
pyshield_encryptor.egg-info/requires.txt
pyshield_encryptor.egg-info/top_level.txt